AUTHORS.rst
CONTRIBUTING.rst
HISTORY.rst
LICENSE
MANIFEST.in
README.md
README.rst
setup.py
tests/batch.json
tests/parse.json
tests/result.json
txgeocodio/__init__.py
txgeocodio/client.py
txgeocodio/config.py
txgeocodio.egg-info/PKG-INFO
txgeocodio.egg-info/SOURCES.txt
txgeocodio.egg-info/dependency_links.txt
txgeocodio.egg-info/not-zip-safe
txgeocodio.egg-info/requires.txt
txgeocodio.egg-info/top_level.txt