Metadata-Version: 1.1
Name: txgeocodio
Version: 0.1.2
Summary: Simple Twisted interface to http://geocod.io
Home-page: https://github.com/trenton42/txgeocodio
Author: Trenton Broughton
Author-email: trenton@devpie.com
License: BSD
Keywords: txgeocodio
Platform: UNKNOWN
Classifier: Development Status :: 2 - Pre-Alpha
Classifier: Intended Audience :: Developers
Classifier: License :: OSI Approved :: BSD License
Classifier: Natural Language :: English
Classifier: Programming Language :: Python :: 2
Classifier: Programming Language :: Python :: 2.6
Classifier: Programming Language :: Python :: 2.7
Classifier: Programming Language :: Python :: 3
Classifier: Programming Language :: Python :: 3.3
